retinaface/__init__.py
retinaface/src/__init__.py
retinaface/src/frozen_graph.pb
retinaface/src/retinaface.py
retinaface-1.1.1.dist-info/LICENSE
retinaface-1.1.1.dist-info/METADATA
retinaface-1.1.1.dist-info/WHEEL
retinaface-1.1.1.dist-info/top_level.txt
retinaface-1.1.1.dist-info/RECORD
