Metadata-Version: 2.1
Name: retinaface
Version: 1.1.1
Summary: face detector
Home-page: https://github.com/heewinkim/retinaface
Author: HEESEUNG KIM
Author-email: heewin.kim@gmail.com
License: MIT
Download-URL: https://github.com/heewinkim/retinaface/archive/master.zip
Platform: UNKNOWN
Classifier: Programming Language :: Python :: 3
Classifier: License :: OSI Approved :: MIT License
Classifier: Operating System :: OS Independent
Requires-Python: >=3
Requires-Dist: tensorflow (==2.5.0)
Requires-Dist: streamlit (==1.10.0)
Requires-Dist: opencv-python-headless (==4.6.0.66)
Requires-Dist: streamlit-webrtc (==0.42.0)
